teedoh_kinter/__init__.py
teedoh_kinter/components.py
teedoh_kinter-0.2.0.dist-info/licenses/LICENSE
teedoh_kinter-0.2.0.dist-info/METADATA
teedoh_kinter-0.2.0.dist-info/WHEEL
teedoh_kinter-0.2.0.dist-info/top_level.txt
teedoh_kinter-0.2.0.dist-info/RECORD
