Metadata-Version: 2.4
Name: teedoh_kinter
Version: 0.2.0
Summary: A superset of TKinter with prebuilt components for straightforward frontends
Author-email: Teedoh <teedohtrackz@gmail.com>
License:                     GNU GENERAL PUBLIC LICENSE
Requires-Python: >=3.12
License-File: LICENSE
Dynamic: license-file
